minis3/__init__.py
minis3/auth.py
minis3/connection.py
minis3/datetime_utils.py
minis3/multipart_upload.py
minis3/pool.py
minis3/request_factory.py
minis3/util.py
minis3-1.0.2.dist-info/METADATA
minis3-1.0.2.dist-info/WHEEL
minis3-1.0.2.dist-info/top_level.txt
minis3-1.0.2.dist-info/RECORD
