Metadata-Version: 2.4
Name: minis3
Version: 1.0.2
Summary: A enhanced fork of tinys3 - A small library for uploading files to S3-compatible storage, with support of async uploads, worker pools, cache headers etc
Home-page: https://github.com/TheGU/minis3/
Author: Pattapong Jantarach
Author-email: Pattapong Jantarach <me@pattapongj.com>
License: MIT
Project-URL: Homepage, https://github.com/TheGU/minis3
Project-URL: Repository, https://github.com/TheGU/minis3.git
Project-URL: Issues, https://github.com/TheGU/minis3/issues
Keywords: amazon,aws,s3,s3-client,upload,minio,s3-compatible
Platform: Any
Classifier: Development Status :: 5 - Production/Stable
Classifier: Intended Audience :: Developers
Classifier: License :: OSI Approved :: MIT License
Classifier: Programming Language :: Python
Classifier: Programming Language :: Python :: 2.7
Classifier: Programming Language :: Python :: 3
Classifier: Programming Language :: Python :: 3.8
Classifier: Programming Language :: Python :: 3.9
Classifier: Programming Language :: Python :: 3.10
Classifier: Programming Language :: Python :: 3.11
Classifier: Programming Language :: Python :: 3.12
Classifier: Topic :: Internet :: WWW/HTTP
Classifier: Topic :: Software Development :: Libraries :: Python Modules
Requires-Python: !=3.0.*,!=3.1.*,!=3.2.*,!=3.3.*,!=3.4.*,!=3.5.*,!=3.6.*,!=3.7.*,>=2.7
Requires-Dist: requests
Dynamic: author
Dynamic: home-page
Dynamic: platform
